PDF4Cat/__init__.py
PDF4Cat/__main__.py
PDF4Cat/cat.py
PDF4Cat/compress.py
PDF4Cat/crypt.py
PDF4Cat/doc.py
PDF4Cat/helpers.py
PDF4Cat/merger.py
PDF4Cat/splitter.py
PDF4Cat/tools.py
PDF4Cat/converter/__init__.py
PDF4Cat/converter/any.py
PDF4Cat/converter/helpers.py
PDF4Cat/converter/images.py
PDF4Cat/converter/ocr.py
PDF4Cat/converter/soffice2pdf.py
PDF4Cat/effects/__init__.py
PDF4Cat/effects/rotate.py
PDF4Cat-0.5.0.dist-info/LICENSE
PDF4Cat-0.5.0.dist-info/METADATA
PDF4Cat-0.5.0.dist-info/WHEEL
PDF4Cat-0.5.0.dist-info/entry_points.txt
PDF4Cat-0.5.0.dist-info/top_level.txt
PDF4Cat-0.5.0.dist-info/RECORD
