Metadata-Version: 2.1
Name: PDF4Cat
Version: 0.5.0
Summary: PDF4Cat Simple and Power tool for processing pdf docs using PyMuPDF
Home-page: https://github.com/BlackCatDevel0per/PDF4Cat
Author: bcdev
Author-email: bcdev@mail.ru
Project-URL: Bug Tracker, https://github.com/BlackCatDevel0per/PDF4Cat/issues
Classifier: Framework :: Django
Classifier: Programming Language :: Python :: 3
Classifier: License :: OSI Approved :: Apache Software License
Classifier: Operating System :: OS Independent
Requires-Python: >=3.7
License-File: LICENSE
Requires-Dist: PyMuPDF (==1.20.0)
Requires-Dist: mammoth (==1.4.19)
Requires-Dist: python-docx (==0.8.11)
Requires-Dist: python-pptx (==0.6.21)
